upstash_vector/__init__.py
upstash_vector/client.py
upstash_vector/core/index_operations.py
upstash_vector/errors.py
upstash_vector/http.py
upstash_vector/py.typed
upstash_vector/types.py
upstash_vector/utils.py
upstash_vector-0.7.1.dist-info/LICENSE
upstash_vector-0.7.1.dist-info/METADATA
upstash_vector-0.7.1.dist-info/WHEEL
upstash_vector-0.7.1.dist-info/RECORD
