Metadata-Version: 2.3
Name: upstash-vector
Version: 0.7.1
Summary: Serverless Vector SDK from Upstash
License: MIT
Keywords: Upstash Vector,Serverless Vector
Author: Upstash
Author-email: support@upstash.com
Maintainer: Upstash
Maintainer-email: support@upstash.com
Requires-Python: >=3.8,<4.0
Classifier: Development Status :: 3 - Alpha
Classifier: Intended Audience :: Developers
Classifier: License :: OSI Approved :: MIT License
Classifier: Operating System :: OS Independent
Classifier: Programming Language :: Python
Classifier: Programming Language :: Python :: 3
Classifier: Programming Language :: Python :: 3.8
Classifier: Programming Language :: Python :: 3.9
Classifier: Programming Language :: Python :: 3.10
Classifier: Programming Language :: Python :: 3.11
Classifier: Programming Language :: Python :: 3.12
Classifier: Programming Language :: Python :: 3.13
Classifier: Programming Language :: Python :: 3 :: Only
Classifier: Programming Language :: Python :: Implementation :: CPython
Classifier: Topic :: Database
Classifier: Topic :: Database :: Front-Ends
Classifier: Topic :: Software Development :: Libraries
Requires-Dist: httpx (>=0.23.0,<1)
Project-URL: Repository, https://github.com/upstash/vector-py
